mt19937predictor.py
mersenne_twister_predictor-0.0.4.data/scripts/mt19937predict
mersenne_twister_predictor-0.0.4.dist-info/DESCRIPTION.rst
mersenne_twister_predictor-0.0.4.dist-info/METADATA
mersenne_twister_predictor-0.0.4.dist-info/RECORD
mersenne_twister_predictor-0.0.4.dist-info/WHEEL
mersenne_twister_predictor-0.0.4.dist-info/metadata.json
mersenne_twister_predictor-0.0.4.dist-info/top_level.txt
